mrafit/__init__.py
mrafit/coeffs.yaml
mrafit/test_gausslets.ipynb
mrafit/unitary_circ_coefficient.py
mrafit/utils.py
mrafit/wavelet_bases.py
mrafit/wavelet_coefficients.py
mrafit-0.1.0.dist-info/LICENSE
mrafit-0.1.0.dist-info/METADATA
mrafit-0.1.0.dist-info/WHEEL
mrafit-0.1.0.dist-info/RECORD
